MANIFEST.in
setup.py
collective/__init__.py
collective.amberjack.core.egg-info/PKG-INFO
collective.amberjack.core.egg-info/SOURCES.txt
collective.amberjack.core.egg-info/dependency_links.txt
collective.amberjack.core.egg-info/entry_points.txt
collective.amberjack.core.egg-info/namespace_packages.txt
collective.amberjack.core.egg-info/not-zip-safe
collective.amberjack.core.egg-info/requires.txt
collective.amberjack.core.egg-info/top_level.txt
collective/amberjack/__init__.py
collective/amberjack/core/README.txt
collective/amberjack/core/__init__.py
collective/amberjack/core/blueprints.py
collective/amberjack/core/configure.zcml
collective/amberjack/core/controlpanel.py
collective/amberjack/core/interfaces.py
collective/amberjack/core/meta.zcml
collective/amberjack/core/profiles.zcml
collective/amberjack/core/registration.py
collective/amberjack/core/skins.py
collective/amberjack/core/skins.zcml
collective/amberjack/core/tool.gif
collective/amberjack/core/tour.py
collective/amberjack/core/tour_converter.py
collective/amberjack/core/tour_manager.py
collective/amberjack/core/utils.py
collective/amberjack/core/validators.py
collective/amberjack/core/vocabulary.py
collective/amberjack/core/zcml.py
collective/amberjack/core/javascript/__init__.py
collective/amberjack/core/javascript/configure.zcml
collective/amberjack/core/javascript/defaults.py
collective/amberjack/core/locales/collective.amberjack.core.pot
collective/amberjack/core/locales/update.sh
collective/amberjack/core/locales/es/LC_MESSAGES/collective.amberjack.core.po
collective/amberjack/core/locales/fr/LC_MESSAGES/collective.amberjack.core.po
collective/amberjack/core/locales/no/LC_MESSAGES/collective.amberjack.core.mo
collective/amberjack/core/locales/no/LC_MESSAGES/collective.amberjack.core.po
collective/amberjack/core/locales/pt-br/LC_MESSAGES/collective.amberjack.core.po
collective/amberjack/core/locales/sl/LC_MESSAGES/collective.amberjack.core.po
collective/amberjack/core/profiles/default/controlpanel.xml
collective/amberjack/core/profiles/default/cssregistry.xml
collective/amberjack/core/profiles/default/jsregistry.xml
collective/amberjack/core/profiles/default/metadata.xml
collective/amberjack/core/profiles/default/skins.xml
collective/amberjack/core/profiles/default/toolset.xml
collective/amberjack/core/skins/collective_amberjack_images/amberjack.png
